gradpy/__init__.py
gradpy/autodiff.py
gradpy/math.py
gradpy/tests/__init__.py
gradpy/tests/test_autodiff.py
gradpy-1.0.0.dist-info/LICENSE
gradpy-1.0.0.dist-info/METADATA
gradpy-1.0.0.dist-info/WHEEL
gradpy-1.0.0.dist-info/top_level.txt
gradpy-1.0.0.dist-info/RECORD
